{
  "__inputs": [
    {
      "name": "DS_PROMETHEUS",
      "label": "Prometheus",
      "description": "",
      "type": "datasource",
      "pluginId": "prometheus",
      "pluginName": "Prometheus"
    }
  ],
  "__requires": [
    {
      "type": "grafana",
      "id": "grafana",
      "name": "Grafana",
      "version": "8.0.0"
    },
    {
      "type": "datasource",
      "id": "prometheus",
      "name": "Prometheus",
      "version": "1.0.0"
    }
  ],
  "annotations": {
    "list": [
      {
        "builtIn": 1,
        "datasource": "-- Grafana --",
        "enable": true,
        "hide": true,
        "iconColor": "rgba(0, 211, 255, 1)",
        "name": "Annotations & Alerts",
        "type": "dashboard"
      }
    ]
  },
  "editable": true,
  "gnetId": null,
  "graphTooltip": 0,
  "id": null,
  "links": [],
  "panels": [
    {
      "collapsed": false,
      "gridPos": {
        "h": 1,
        "w": 24,
        "x": 0,
        "y": 0
      },
      "id": 100,
      "panels": [],
      "title": "🚦 Resumo Executivo (Golden Signals)",
      "type": "row"
    },
    {
      "datasource": "${DS_PROMETHEUS}",
      "fieldConfig": {
        "defaults": {
          "color": {
            "mode": "thresholds"
          },
          "mappings": [],
          "thresholds": {
            "mode": "absolute",
            "steps": [
              {
                "color": "green",
                "value": null
              }
            ]
          },
          "unit": "reqps"
        },
        "overrides": []
      },
      "gridPos": {
        "h": 5,
        "w": 6,
        "x": 0,
        "y": 1
      },
      "id": 101,
      "options": {
        "colorMode": "value",
        "graphMode": "area",
        "justifyMode": "auto",
        "orientation": "auto",
        "reduceOptions": {
          "calcs": [
            "lastNotNull"
          ],
          "fields": "",
          "values": false
        },
        "textMode": "auto"
      },
      "pluginVersion": "8.0.0",
      "targets": [
        {
          "expr": "sum(rate(http_server_requests_seconds_count{application=\"$application\", instance=\"$instance\"}[1m]))",
          "legendFormat": "Global RPS"
        }
      ],
      "title": "RPS Global",
      "type": "stat"
    },
    {
      "datasource": "${DS_PROMETHEUS}",
      "fieldConfig": {
        "defaults": {
          "color": {
            "mode": "thresholds"
          },
          "mappings": [],
          "thresholds": {
            "mode": "absolute",
            "steps": [
              {
                "color": "green",
                "value": null
              },
              {
                "color": "red",
                "value": 0.01
              }
            ]
          },
          "unit": "percent"
        },
        "overrides": []
      },
      "gridPos": {
        "h": 5,
        "w": 6,
        "x": 6,
        "y": 1
      },
      "id": 102,
      "options": {
        "colorMode": "value",
        "graphMode": "area",
        "justifyMode": "auto",
        "orientation": "auto",
        "reduceOptions": {
          "calcs": [
            "lastNotNull"
          ],
          "fields": "",
          "values": false
        },
        "textMode": "auto"
      },
      "pluginVersion": "8.0.0",
      "targets": [
        {
          "expr": "sum(rate(http_server_requests_seconds_count{application=\"$application\", instance=\"$instance\", status=~\"5..\"}[1m])) / sum(rate(http_server_requests_seconds_count{application=\"$application\", instance=\"$instance\"}[1m]))",
          "legendFormat": "Error Rate"
        }
      ],
      "title": "Taxa de Erro (5xx)",
      "type": "stat"
    },
    {
      "datasource": "${DS_PROMETHEUS}",
      "fieldConfig": {
        "defaults": {
          "color": {
            "mode": "thresholds"
          },
          "mappings": [],
          "thresholds": {
            "mode": "absolute",
            "steps": [
              {
                "color": "green",
                "value": null
              },
              {
                "color": "orange",
                "value": 0.5
              },
              {
                "color": "red",
                "value": 1
              }
            ]
          },
          "unit": "s"
        },
        "overrides": []
      },
      "gridPos": {
        "h": 5,
        "w": 6,
        "x": 12,
        "y": 1
      },
      "id": 103,
      "options": {
        "colorMode": "value",
        "graphMode": "area",
        "justifyMode": "auto",
        "orientation": "auto",
        "reduceOptions": {
          "calcs": [
            "lastNotNull"
          ],
          "fields": "",
          "values": false
        },
        "textMode": "auto"
      },
      "pluginVersion": "8.0.0",
      "targets": [
        {
          "expr": "histogram_quantile(0.95, sum(rate(http_server_requests_seconds_bucket{application=\"$application\", instance=\"$instance\"}[1m])) by (le))",
          "legendFormat": "P95 Latency"
        }
      ],
      "title": "Latência Global (p95)",
      "type": "stat"
    },
    {
      "datasource": "${DS_PROMETHEUS}",
      "fieldConfig": {
        "defaults": {
          "color": {
            "mode": "thresholds"
          },
          "mappings": [],
          "thresholds": {
            "mode": "absolute",
            "steps": [
              {
                "color": "green",
                "value": null
              }
            ]
          },
          "unit": "s"
        },
        "overrides": []
      },
      "gridPos": {
        "h": 5,
        "w": 6,
        "x": 18,
        "y": 1
      },
      "id": 104,
      "options": {
        "colorMode": "value",
        "graphMode": "area",
        "justifyMode": "auto",
        "orientation": "auto",
        "reduceOptions": {
          "calcs": [
            "lastNotNull"
          ],
          "fields": "",
          "values": false
        },
        "textMode": "auto"
      },
      "pluginVersion": "8.0.0",
      "targets": [
        {
          "expr": "process_uptime_seconds{application=\"$application\", instance=\"$instance\"}",
          "legendFormat": "Uptime"
        }
      ],
      "title": "Uptime",
      "type": "stat"
    },
    {
      "collapsed": false,
      "gridPos": {
        "h": 1,
        "w": 24,
        "x": 0,
        "y": 6
      },
      "id": 200,
      "panels": [],
      "title": "📈 Performance da API (HTTP)",
      "type": "row"
    },
    {
      "datasource": "${DS_PROMETHEUS}",
      "fieldConfig": {
        "defaults": {
          "color": {
            "mode": "palette-classic"
          },
          "unit": "reqps"
        },
        "overrides": []
      },
      "gridPos": {
        "h": 8,
        "w": 12,
        "x": 0,
        "y": 7
      },
      "id": 201,
      "options": {
        "legend": {
          "calcs": [],
          "displayMode": "list",
          "placement": "bottom"
        },
        "tooltip": {
          "mode": "multi"
        }
      },
      "targets": [
        {
          "expr": "sum(rate(http_server_requests_seconds_count{application=\"$application\", instance=\"$instance\"}[1m])) by (uri)",
          "legendFormat": "{{uri}}",
          "refId": "A"
        }
      ],
      "title": "RPS por Endpoint",
      "type": "timeseries"
    },
    {
      "datasource": "${DS_PROMETHEUS}",
      "fieldConfig": {
        "defaults": {
          "color": {
            "mode": "palette-classic"
          },
          "unit": "ms"
        },
        "overrides": []
      },
      "gridPos": {
        "h": 8,
        "w": 12,
        "x": 12,
        "y": 7
      },
      "id": 202,
      "options": {
        "legend": {
          "calcs": [],
          "displayMode": "list",
          "placement": "bottom"
        },
        "tooltip": {
          "mode": "multi"
        }
      },
      "targets": [
        {
          "expr": "histogram_quantile(0.95, sum(rate(http_server_requests_seconds_bucket{application=\"$application\", instance=\"$instance\"}[1m])) by (le, uri))",
          "legendFormat": "p95 {{uri}}",
          "refId": "A"
        }
      ],
      "title": "Latência p95 por Endpoint",
      "type": "timeseries"
    },
    {
      "collapsed": false,
      "gridPos": {
        "h": 1,
        "w": 24,
        "x": 0,
        "y": 15
      },
      "id": 300,
      "panels": [],
      "title": "💾 Banco de Dados (PostgreSQL / HikariCP)",
      "type": "row"
    },
    {
      "datasource": "${DS_PROMETHEUS}",
      "fieldConfig": {
        "defaults": {
          "color": {
            "mode": "palette-classic"
          },
          "unit": "short"
        },
        "overrides": []
      },
      "gridPos": {
        "h": 8,
        "w": 8,
        "x": 0,
        "y": 16
      },
      "id": 301,
      "options": {
        "legend": {
          "calcs": [],
          "displayMode": "list",
          "placement": "bottom"
        },
        "tooltip": {
          "mode": "multi"
        }
      },
      "targets": [
        {
          "expr": "hikaricp_connections_active{application=\"$application\", instance=\"$instance\"}",
          "legendFormat": "Ativas",
          "refId": "A"
        },
        {
          "expr": "hikaricp_connections_idle{application=\"$application\", instance=\"$instance\"}",
          "legendFormat": "Inativas (Idle)",
          "refId": "B"
        },
        {
          "expr": "hikaricp_connections_pending{application=\"$application\", instance=\"$instance\"}",
          "legendFormat": "Pendentes",
          "refId": "C"
        }
      ],
      "title": "Pool de Conexões Hikari",
      "type": "timeseries"
    },
    {
      "datasource": "${DS_PROMETHEUS}",
      "fieldConfig": {
        "defaults": {
          "color": {
            "mode": "palette-classic"
          },
          "unit": "ms"
        },
        "overrides": []
      },
      "gridPos": {
        "h": 8,
        "w": 8,
        "x": 8,
        "y": 16
      },
      "id": 302,
      "options": {
        "legend": {
          "calcs": [],
          "displayMode": "list",
          "placement": "bottom"
        },
        "tooltip": {
          "mode": "multi"
        }
      },
      "targets": [
        {
          "expr": "hikaricp_connections_acquire_seconds_max{application=\"$application\", instance=\"$instance\"}",
          "legendFormat": "Max Acquire Time",
          "refId": "A"
        }
      ],
      "title": "Tempo de Aquisição de Conexão",
      "type": "timeseries"
    },
    {
      "datasource": "${DS_PROMETHEUS}",
      "fieldConfig": {
        "defaults": {
          "color": {
            "mode": "palette-classic"
          },
          "unit": "short"
        },
        "overrides": []
      },
      "gridPos": {
        "h": 8,
        "w": 8,
        "x": 16,
        "y": 16
      },
      "id": 303,
      "options": {
        "legend": {
          "calcs": [],
          "displayMode": "list",
          "placement": "bottom"
        },
        "tooltip": {
          "mode": "multi"
        }
      },
      "targets": [
        {
          "expr": "hikaricp_connections_timeout_total{application=\"$application\", instance=\"$instance\"}",
          "legendFormat": "Timeouts",
          "refId": "A"
        }
      ],
      "title": "Timeouts do Pool de Conexões",
      "type": "timeseries"
    },
    {
      "collapsed": false,
      "gridPos": {
        "h": 1,
        "w": 24,
        "x": 0,
        "y": 24
      },
      "id": 400,
      "panels": [],
      "title": "⚡ Cache (Redis)",
      "type": "row"
    },
    {
      "datasource": "${DS_PROMETHEUS}",
      "fieldConfig": {
        "defaults": {
          "color": {
            "mode": "palette-classic"
          },
          "unit": "percent"
        },
        "overrides": []
      },
      "gridPos": {
        "h": 8,
        "w": 12,
        "x": 0,
        "y": 25
      },
      "id": 401,
      "options": {
        "legend": {
          "calcs": [],
          "displayMode": "list",
          "placement": "bottom"
        },
        "tooltip": {
          "mode": "multi"
        }
      },
      "targets": [
        {
          "expr": "sum(rate(cache_gets_total{application=\"$application\", cache=\"accounts\", result=\"hit\"}[1m])) / sum(rate(cache_gets_total{application=\"$application\", cache=\"accounts\"}[1m])) * 100",
          "legendFormat": "Accounts Hit %",
          "refId": "A"
        },
        {
          "expr": "sum(rate(cache_gets_total{application=\"$application\", cache=\"users\", result=\"hit\"}[1m])) / sum(rate(cache_gets_total{application=\"$application\", cache=\"users\"}[1m])) * 100",
          "legendFormat": "Users Hit %",
          "refId": "B"
        }
      ],
      "title": "Taxa de Acerto do Cache (Hit %)",
      "type": "timeseries"
    },
    {
      "datasource": "${DS_PROMETHEUS}",
      "fieldConfig": {
        "defaults": {
          "color": {
            "mode": "palette-classic"
          },
          "unit": "ops"
        },
        "overrides": []
      },
      "gridPos": {
        "h": 8,
        "w": 12,
        "x": 12,
        "y": 25
      },
      "id": 402,
      "options": {
        "legend": {
          "calcs": [],
          "displayMode": "list",
          "placement": "bottom"
        },
        "tooltip": {
          "mode": "multi"
        }
      },
      "targets": [
        {
          "expr": "sum(rate(cache_puts_total{application=\"$application\"}[1m])) by (cache)",
          "legendFormat": "{{cache}} puts",
          "refId": "A"
        },
        {
          "expr": "sum(rate(cache_gets_total{application=\"$application\", result=\"miss\"}[1m])) by (cache)",
          "legendFormat": "{{cache}} misses",
          "refId": "B"
        }
      ],
      "title": "Operações de Cache (Put/Miss)",
      "type": "timeseries"
    },
    {
      "collapsed": false,
      "gridPos": {
        "h": 1,
        "w": 24,
        "x": 0,
        "y": 33
      },
      "id": 500,
      "panels": [],
      "title": "📬 Mensageria (Kafka)",
      "type": "row"
    },
    {
      "datasource": "${DS_PROMETHEUS}",
      "fieldConfig": {
        "defaults": {
          "color": {
            "mode": "palette-classic"
          },
          "unit": "short"
        },
        "overrides": []
      },
      "gridPos": {
        "h": 8,
        "w": 12,
        "x": 0,
        "y": 34
      },
      "id": 501,
      "options": {
        "legend": {
          "calcs": [],
          "displayMode": "list",
          "placement": "bottom"
        },
        "tooltip": {
          "mode": "multi"
        }
      },
      "targets": [
        {
          "expr": "sum(kafka_consumer_fetch_manager_records_lag_max{client_id=~\"$application.*\"}) by (topic)",
          "legendFormat": "Lag {{topic}}",
          "refId": "A"
        }
      ],
      "title": "Lag do Consumidor Kafka",
      "type": "timeseries"
    },
    {
      "datasource": "${DS_PROMETHEUS}",
      "fieldConfig": {
        "defaults": {
          "color": {
            "mode": "palette-classic"
          },
          "unit": "bytes"
        },
        "overrides": []
      },
      "gridPos": {
        "h": 8,
        "w": 12,
        "x": 12,
        "y": 34
      },
      "id": 502,
      "options": {
        "legend": {
          "calcs": [],
          "displayMode": "list",
          "placement": "bottom"
        },
        "tooltip": {
          "mode": "multi"
        }
      },
      "targets": [
        {
          "expr": "rate(kafka_producer_topic_record_send_total{client_id=~\"$application.*\"}[1m])",
          "legendFormat": "Produzidas/s",
          "refId": "A"
        },
        {
          "expr": "rate(kafka_consumer_fetch_manager_records_consumed_total{client_id=~\"$application.*\"}[1m])",
          "legendFormat": "Consumidas/s",
          "refId": "B"
        }
      ],
      "title": "Taxa de Produção/Consumo Kafka",
      "type": "timeseries"
    },
    {
      "collapsed": false,
      "gridPos": {
        "h": 1,
        "w": 24,
        "x": 0,
        "y": 42
      },
      "id": 600,
      "panels": [],
      "title": "🧠 JVM Internals",
      "type": "row"
    },
    {
      "datasource": "${DS_PROMETHEUS}",
      "fieldConfig": {
        "defaults": {
          "color": {
            "mode": "palette-classic"
          },
          "unit": "bytes"
        },
        "overrides": []
      },
      "gridPos": {
        "h": 8,
        "w": 12,
        "x": 0,
        "y": 43
      },
      "id": 601,
      "options": {
        "legend": {
          "calcs": [],
          "displayMode": "list",
          "placement": "bottom"
        },
        "tooltip": {
          "mode": "multi"
        }
      },
      "targets": [
        {
          "expr": "jvm_memory_used_bytes{application=\"$application\", instance=\"$instance\", area=\"heap\"}",
          "legendFormat": "Heap Used",
          "refId": "A"
        },
        {
          "expr": "jvm_memory_committed_bytes{application=\"$application\", instance=\"$instance\", area=\"heap\"}",
          "legendFormat": "Heap Committed",
          "refId": "B"
        }
      ],
      "title": "Uso de Memória Heap",
      "type": "timeseries"
    },
    {
      "datasource": "${DS_PROMETHEUS}",
      "fieldConfig": {
        "defaults": {
          "color": {
            "mode": "palette-classic"
          },
          "unit": "ms"
        },
        "overrides": []
      },
      "gridPos": {
        "h": 8,
        "w": 12,
        "x": 12,
        "y": 43
      },
      "id": 602,
      "options": {
        "legend": {
          "calcs": [],
          "displayMode": "list",
          "placement": "bottom"
        },
        "tooltip": {
          "mode": "multi"
        }
      },
      "targets": [
        {
          "expr": "rate(jvm_gc_pause_seconds_sum{application=\"$application\", instance=\"$instance\"}[1m]) * 1000",
          "legendFormat": "GC Pause ({{action}})",
          "refId": "A"
        }
      ],
      "title": "Pausas de Garbage Collection (Stop-the-World)",
      "type": "timeseries"
    },
    {
      "datasource": "${DS_PROMETHEUS}",
      "fieldConfig": {
        "defaults": {
          "color": {
            "mode": "palette-classic"
          },
          "unit": "short"
        },
        "overrides": []
      },
      "gridPos": {
        "h": 8,
        "w": 12,
        "x": 0,
        "y": 51
      },
      "id": 603,
      "options": {
        "legend": {
          "calcs": [],
          "displayMode": "list",
          "placement": "bottom"
        },
        "tooltip": {
          "mode": "multi"
        }
      },
      "targets": [
        {
          "expr": "jvm_threads_live_threads{application=\"$application\", instance=\"$instance\"}",
          "legendFormat": "Live",
          "refId": "A"
        },
        {
          "expr": "jvm_threads_daemon_threads{application=\"$application\", instance=\"$instance\"}",
          "legendFormat": "Daemon",
          "refId": "B"
        },
        {
          "expr": "jvm_threads_virtual_threads{application=\"$application\", instance=\"$instance\"}",
          "legendFormat": "Virtual",
          "refId": "C"
        }
      ],
      "title": "Threads (Plataforma vs Virtuais)",
      "type": "timeseries"
    },
    {
      "datasource": "${DS_PROMETHEUS}",
      "fieldConfig": {
        "defaults": {
          "color": {
            "mode": "palette-classic"
          },
          "unit": "percentunit"
        },
        "overrides": []
      },
      "gridPos": {
        "h": 8,
        "w": 12,
        "x": 12,
        "y": 51
      },
      "id": 604,
      "options": {
        "legend": {
          "calcs": [],
          "displayMode": "list",
          "placement": "bottom"
        },
        "tooltip": {
          "mode": "multi"
        }
      },
      "targets": [
        {
          "expr": "process_cpu_usage{application=\"$application\", instance=\"$instance\"}",
          "legendFormat": "Uso de CPU do Processo",
          "refId": "A"
        }
      ],
      "title": "Uso de CPU (JVM)",
      "type": "timeseries"
    }
  ],
  "refresh": "10s",
  "schemaVersion": 30,
  "style": "dark",
  "tags": [
    "spring-boot",
    "observability",
    "expert"
  ],
  "templating": {
    "list": [
      {
        "current": {
          "selected": true,
          "text": "Prometheus",
          "value": "Prometheus"
        },
        "hide": 0,
        "includeAll": false,
        "label": "Datasource",
        "multi": false,
        "name": "DS_PROMETHEUS",
        "options": [],
        "query": "prometheus",
        "refresh": 1,
        "regex": "",
        "skipUrlSync": false,
        "type": "datasource"
      },
      {
        "allValue": null,
        "current": {
          "selected": true,
          "text": "ledger-service",
          "value": "ledger-service"
        },
        "datasource": "${DS_PROMETHEUS}",
        "definition": "label_values(up, application)",
        "hide": 0,
        "includeAll": false,
        "label": "Application",
        "multi": false,
        "name": "application",
        "options": [],
        "query": {
          "query": "label_values(up, application)",
          "refId": "StandardVariableQuery"
        },
        "refresh": 2,
        "regex": "",
        "skipUrlSync": false,
        "sort": 1,
        "type": "query"
      },
      {
        "allValue": null,
        "current": {
          "isNone": true,
          "text": "None",
          "value": ""
        },
        "datasource": "${DS_PROMETHEUS}",
        "definition": "label_values(up{application=\"$application\"}, instance)",
        "hide": 0,
        "includeAll": true,
        "label": "Instance",
        "multi": true,
        "name": "instance",
        "options": [],
        "query": {
          "query": "label_values(up{application=\"$application\"}, instance)",
          "refId": "StandardVariableQuery"
        },
        "refresh": 2,
        "regex": "",
        "skipUrlSync": false,
        "sort": 1,
        "type": "query"
      }
    ]
  },
  "time": {
    "from": "now-15m",
    "to": "now"
  },
  "timepicker": {},
  "timezone": "browser",
  "title": "Ledger Service - Observabilidade Completa",
  "uid": "ledger-service-full",
  "version": 1
}
